[{"moduleId":"FINX103","rank":1,"template":"readonly","templateOptions":{"styles":{"backgroundImage":"url(/assets/images/modules/demo-FINX103/task-bg.png)"}},"content":{"sections":[{"type":"image","value":"/assets/images/modules/demo-FINX103/question-mark.png","style":{"height":"6rem"}},{"type":"text-heading","value":"Quick Review Before the Challenge!","style":{"fontWeight":700,"fontSize":"2rem"}},{"type":"text-heading","value":"Before we dive into the Financial IQ Test,\n let's have a quick game-based revision. ","style":{"fontWeight":700,"fontSize":"2rem"}}],"actions":[{"id":1,"variant":"primary","contents":[{"type":"text","value":"Let's Go","style":{"minWidth":"8rem"}}]}]},"characters":[],"prompts":[],"dialogues":[],"active":true,"id":"6557a42c782e953a467171ca"},{"moduleId":"FINX103","rank":2,"template":"activity-card-flip-game","templateOptions":{"styles":{"backgroundImage":"url(/assets/images/modules/demo-FINX103/task-bg.png)"}},"characters":[],"prompts":[],"dialogues":[],"cardFlipGame":{"question":[{"type":"text-heading","value":"Flip the cards and find the matching pairs to revise key financial concepts","style":{"width":"46.375rem","fontSize":"2rem","fontWeight":700}}],"cards":[{"code":1,"backSections":[{"type":"text","value":"Can’t be bought with money","style":{"color":"#fff","fontSize":"1.5rem","padding":"0.8rem"}}],"backCardStyle":{"backgroundColor":"#EB2F54"}},{"code":2,"backSections":[{"type":"text","value":"Trading Plants for Vegetables","style":{"color":"#DD5D1A","fontSize":"1.5rem","padding":"0.8rem"}}],"backCardStyle":{"backgroundColor":"#F7CC88"}},{"code":3,"backSections":[{"type":"text","value":"Payment for Goods & Services","style":{"color":"#902936","fontSize":"1.5rem","padding":"0.8rem"}}],"backCardStyle":{"backgroundColor":"#E6B7BD"}},{"code":4,"backSections":[{"type":"text","value":"Choosing one over another","style":{"color":"#15716D","fontSize":"1.5rem","padding":"0.8rem"}}],"backCardStyle":{"backgroundColor":"#64CECE"}},{"code":3,"backSections":[{"type":"image","value":"/assets/images/modules/demo-FINX103/card-flip-1.png","style":{"height":"100%","width":"100%"}}],"backCardStyle":{"backgroundColor":"#EB2F54","padding":"0","overflow":"hidden"}},{"code":2,"backSections":[{"type":"image","value":"/assets/images/modules/demo-FINX103/card-flip-2.png","style":{"height":"100%","width":"100%"}}],"backCardStyle":{"backgroundColor":"#F7CC88","padding":"0","overflow":"hidden"}},{"code":1,"backSections":[{"type":"image","value":"/assets/images/modules/demo-FINX103/card-flip-3.png","style":{"height":"100%","width":"100%"}}],"backCardStyle":{"backgroundColor":"#E6B7BD","padding":"0","overflow":"hidden"}},{"code":4,"backSections":[{"type":"image","value":"/assets/images/modules/demo-FINX103/card-flip-4.png","style":{"height":"100%","width":"100%"}}],"backCardStyle":{"backgroundColor":"#64CECE","padding":"0","overflow":"hidden"}}]},"active":true,"id":"6557a42c782e953a467171cd"},{"moduleId":"FINX103","rank":3,"template":"readonly","templateOptions":{"styles":{"backgroundImage":"url(/assets/images/modules/demo-FINX103/task-bg.png)"}},"content":{"sections":[{"type":"image","value":"/assets/images/modules/demo-FINX103/knight.png","style":{"height":"7.5rem"}},{"type":"text-heading","value":"Global Financial IQ Test"},{"type":"text","value":"Test Your Financial Knowledge and \n Skills on a Global Scale","style":{"fontWeight":"500"}}],"actions":[{"id":1,"variant":"primary","contents":[{"type":"text","value":"Start","style":{"minWidth":"8rem"}}]}]},"characters":[],"prompts":[],"dialogues":[],"active":true,"id":"6557a42c782e953a467171d0"},{"moduleId":"FINX103","rank":4,"template":"activity-character-feedback","templateOptions":{"styles":{"backgroundImage":"url(/assets/images/backgrounds/task-bg.png)","backgroundSize":"100% 100%","backgroundPosition":"center"}},"characters":[],"prompts":[],"dialogues":[],"audio":{"sources":["/assets/modules/FINX/audio/feedback-greenline-01.mp3"]},"characterFeedbackActivity":{"animateStyles":"top-bottom","isRequired":true,"stepStyle":{"boxShadow":"0px 0.6rem 0px 0px #87CEEB"},"title":[{"type":"text-heading","value":"What do you feel about the\n overall experience of this module?"}],"type":"option-button","multiSelect":false,"optionsFlow":"horizontal","options":[{"id":1,"content":[{"type":"image","value":"/assets/modules/FINX001/image/emojifun3.png","style":{"width":"06rem","height":"06rem","maxHeight":"06rem"}},{"type":"text-medium","value":"It was \ninteresting","style":{"fontWeight":800}}],"goToStep":"step3","score":5},{"id":2,"content":[{"type":"image","value":"/assets/modules/FINX001/image/emojifun2.png","style":{"width":"06rem","height":"06rem","maxHeight":"06rem"}},{"type":"text-medium","value":"Moderately\n interesting","style":{"fontWeight":800}}],"goToStep":"step3","score":3},{"id":3,"content":[{"type":"image","value":"/assets/modules/FINX001/image/emojifun1.png","style":{"width":"06rem","height":"06rem","maxHeight":"06rem"}},{"type":"text-medium","value":"Not interesting\n at all","style":{"fontWeight":800}}],"goToStep":"step4","score":1}],"actions":[{"id":1,"variant":"primary","contents":[{"type":"text","value":"Ok"}]}],"tagLabel":"feedback_module_end_finlit","characters":[{"type":"animation","activeAnimation":"asking","idleAnimation":"idle","characterStyle":{"height":"30rem","width":"110%"},"animations":[{"type":"json","value":"/assets/animations/greenline.json"},{"type":"atlas","value":"/assets/animations/greenline.atlas"}],"dialogues":[{"type":"text","value":"Hey! Ms. Greenline here."}]}]},"active":true,"id":"669768ff28604ff158936cf8"}]